boox_annotations_to_anki/__init__.py
boox_annotations_to_anki/__main__.py
boox_annotations_to_anki/api.py
boox_annotations_to_anki/cli.py
boox_annotations_to_anki/constants.py
boox_annotations_to_anki/db.py
boox_annotations_to_anki-1.0.1.dist-info/AUTHORS.rst
boox_annotations_to_anki-1.0.1.dist-info/LICENSE
boox_annotations_to_anki-1.0.1.dist-info/METADATA
boox_annotations_to_anki-1.0.1.dist-info/WHEEL
boox_annotations_to_anki-1.0.1.dist-info/entry_points.txt
boox_annotations_to_anki-1.0.1.dist-info/top_level.txt
boox_annotations_to_anki-1.0.1.dist-info/RECORD
