Metadata-Version: 2.1
Name: boox-annotations-to-anki
Version: 1.0.1
Summary: Create cards in Anki from your Onyx Boox annotations.
Home-page: https://github.com/coddingtonbear/boox-annotations-to-anki
Author: Adam Coddington
Author-email: me@adamcoddington.net
License: MIT
Project-URL: Changelog, https://github.com/coddingtonbear/boox-annotations-to-anki/blob/master/CHANGELOG.rst
Project-URL: Issue Tracker, https://github.com/coddingtonbear/boox-annotations-to-anki/issues
Platform: UNKNOWN
Classifier: Development Status :: 5 - Production/Stable
Classifier: Intended Audience :: Developers
Classifier: License :: OSI Approved :: MIT License
Classifier: Operating System :: Unix
Classifier: Operating System :: POSIX
Classifier: Operating System :: Microsoft :: Windows
Classifier: Programming Language :: Python
Classifier: Programming Language :: Python :: 3
Classifier: Programming Language :: Python :: 3 :: Only
Classifier: Programming Language :: Python :: 3.6
Classifier: Programming Language :: Python :: 3.7
Classifier: Programming Language :: Python :: 3.8
Classifier: Programming Language :: Python :: 3.9
Classifier: Programming Language :: Python :: Implementation :: CPython
Classifier: Programming Language :: Python :: Implementation :: PyPy
Classifier: Topic :: Utilities
Requires-Python: >=3.6
License-File: LICENSE
License-File: AUTHORS.rst
Requires-Dist: requests (<3.0,>=2.26.0)
Requires-Dist: boox-annotation-parser (<1.0,>=0.1)
Requires-Dist: rich (<11.0,>=10.7.0)
Requires-Dist: appdirs (<2.0,>=1.4.4)
